sphinx_version_warning-1.1.2.dist-info/METADATA
sphinx_version_warning-1.1.2.dist-info/RECORD
sphinx_version_warning-1.1.2.dist-info/WHEEL
sphinx_version_warning-1.1.2.dist-info/top_level.txt
versionwarning/__init__.py
versionwarning/banner.py
versionwarning/extension.py
versionwarning/readthedocs.py
versionwarning/signals.py
versionwarning/test_json.py
versionwarning/_static/js/versionwarning.js
