Metadata-Version: 2.1
Name: sphinx-version-warning
Version: 1.1.2
Summary: Sphinx extension to add a warning banner
Home-page: https://github.com/humitos/sphinx-version-warning
Author: Manuel Kaufmann
Author-email: humitos@gmail.com
License: UNKNOWN
Platform: UNKNOWN
Classifier: Programming Language :: Python :: 3
Classifier: License :: OSI Approved :: MIT License
Classifier: Operating System :: OS Independent
Requires-Dist: sphinx
